chesstab/__init__.py
chesstab/chessgames.py
chesstab/chessgames_winedptchunk.py
chesstab/chessgames_winedptmulti.py
chesstab/apsw/__init__.py
chesstab/apsw/database.py
chesstab/apsw/database_du.py
chesstab/basecore/__init__.py
chesstab/basecore/analysis_index.py
chesstab/basecore/analysisds.py
chesstab/basecore/cqlds.py
chesstab/basecore/database.py
chesstab/basecore/fullposition.py
chesstab/basecore/fullpositionds.py
chesstab/basecore/selection.py
chesstab/basecore/selectionds.py
chesstab/berkeleydb/__init__.py
chesstab/berkeleydb/database.py
chesstab/berkeleydb/database_du.py
chesstab/core/__init__.py
chesstab/core/analysis.py
chesstab/core/chessrecord.py
chesstab/core/constants.py
chesstab/core/cqlpgnify.py
chesstab/core/cqlstatement.py
chesstab/core/engine.py
chesstab/core/enginecommands.py
chesstab/core/export_chessql.py
chesstab/core/export_game.py
chesstab/core/export_pgn_import_format.py
chesstab/core/export_repertoire.py
chesstab/core/export_selection_rule.py
chesstab/core/filespec.py
chesstab/core/lexer.py
chesstab/core/pgn.py
chesstab/core/pgnify.py
chesstab/core/querystatement.py
chesstab/core/uci.py
chesstab/core/uci_to_pgn.py
chesstab/core/utilities.py
chesstab/cql/__init__.py
chesstab/cql/querycontainer.py
chesstab/cql/queryevaluator.py
chesstab/cql/runcql.py
chesstab/db/__init__.py
chesstab/db/database.py
chesstab/db/database_du.py
chesstab/db_tkinter/__init__.py
chesstab/db_tkinter/database.py
chesstab/db_tkinter/database_du.py
chesstab/dpt/__init__.py
chesstab/dpt/database.py
chesstab/dpt/database_du.py
chesstab/dpt/dptnofistat.py
chesstab/fonts/CASEFONT.TTF
chesstab/fonts/LUCEFONT.TTF
chesstab/fonts/MERIFONT.TTF
chesstab/fonts/MOTIFONT.TTF
chesstab/fonts/cases.zip
chesstab/fonts/lucen.zip
chesstab/fonts/merid.zip
chesstab/fonts/motif.zip
chesstab/gnu/__init__.py
chesstab/gnu/database.py
chesstab/gnu/database_du.py
chesstab/gui/__init__.py
chesstab/gui/_lead_trail.py
chesstab/gui/_score_scaffold.py
chesstab/gui/analysisscore.py
chesstab-8.2.dist-info/licenses/LICENCE
chesstab-8.2.dist-info/METADATA
chesstab-8.2.dist-info/WHEEL
chesstab-8.2.dist-info/top_level.txt
chesstab-8.2.dist-info/RECORD
